{"nodes": [{"id": "e_onedrive_desktop_agri_360_agri_360_programs_agriconnect360web_src_pages_aipage_jsx", "label": "AIPage.jsx", "file_type": "code", "source_file": "E:\\OneDrive\\Desktop\\AGRI_360\\AGRI_360_PROGRAMS\\AgriConnect360Web\\src\\pages\\AIPage.jsx", "source_location": "L1"}, {"id": "pages_aipage_istelugutext", "label": "isTeluguText()", "file_type": "code", "source_file": "E:\\OneDrive\\Desktop\\AGRI_360\\AGRI_360_PROGRAMS\\AgriConnect360Web\\src\\pages\\AIPage.jsx", "source_location": "L46"}, {"id": "pages_aipage_buildprompt", "label": "buildPrompt()", "file_type": "code", "source_file": "E:\\OneDrive\\Desktop\\AGRI_360\\AGRI_360_PROGRAMS\\AgriConnect360Web\\src\\pages\\AIPage.jsx", "source_location": "L62"}, {"id": "pages_aipage_callgroq", "label": "callGroq()", "file_type": "code", "source_file": "E:\\OneDrive\\Desktop\\AGRI_360\\AGRI_360_PROGRAMS\\AgriConnect360Web\\src\\pages\\AIPage.jsx", "source_location": "L123"}, {"id": "pages_aipage_callgemini", "label": "callGemini()", "file_type": "code", "source_file": "E:\\OneDrive\\Desktop\\AGRI_360\\AGRI_360_PROGRAMS\\AgriConnect360Web\\src\\pages\\AIPage.jsx", "source_location": "L143"}, {"id": "pages_aipage_callaiengine", "label": "callAIEngine()", "file_type": "code", "source_file": "E:\\OneDrive\\Desktop\\AGRI_360\\AGRI_360_PROGRAMS\\AgriConnect360Web\\src\\pages\\AIPage.jsx", "source_location": "L161"}, {"id": "pages_aipage_field", "label": "Field()", "file_type": "code", "source_file": "E:\\OneDrive\\Desktop\\AGRI_360\\AGRI_360_PROGRAMS\\AgriConnect360Web\\src\\pages\\AIPage.jsx", "source_location": "L172"}, {"id": "pages_aipage_getsuggestions", "label": "getSuggestions()", "file_type": "code", "source_file": "E:\\OneDrive\\Desktop\\AGRI_360\\AGRI_360_PROGRAMS\\AgriConnect360Web\\src\\pages\\AIPage.jsx", "source_location": "L197"}, {"id": "pages_aipage_aipage", "label": "AIPage()", "file_type": "code", "source_file": "E:\\OneDrive\\Desktop\\AGRI_360\\AGRI_360_PROGRAMS\\AgriConnect360Web\\src\\pages\\AIPage.jsx", "source_location": "L207"}], "edges": [{"source": "e_onedrive_desktop_agri_360_agri_360_programs_agriconnect360web_src_pages_aipage_jsx", "target": "react", "relation": "imports_from", "confidence": "EXTRACTED", "source_file": "E:\\OneDrive\\Desktop\\AGRI_360\\AGRI_360_PROGRAMS\\AgriConnect360Web\\src\\pages\\AIPage.jsx", "source_location": "L1", "weight": 1.0}, {"source": "e_onedrive_desktop_agri_360_agri_360_programs_agriconnect360web_src_pages_aipage_jsx", "target": "e_onedrive_desktop_agri_360_agri_360_programs_agriconnect360web_src_lib_hooks_useauth", "relation": "imports_from", "confidence": "EXTRACTED", "source_file": "E:\\OneDrive\\Desktop\\AGRI_360\\AGRI_360_PROGRAMS\\AgriConnect360Web\\src\\pages\\AIPage.jsx", "source_location": "L2", "weight": 1.0}, {"source": "e_onedrive_desktop_agri_360_agri_360_programs_agriconnect360web_src_pages_aipage_jsx", "target": "pages_aipage_istelugutext", "relation": "contains", "confidence": "EXTRACTED", "source_file": "E:\\OneDrive\\Desktop\\AGRI_360\\AGRI_360_PROGRAMS\\AgriConnect360Web\\src\\pages\\AIPage.jsx", "source_location": "L46", "weight": 1.0}, {"source": "e_onedrive_desktop_agri_360_agri_360_programs_agriconnect360web_src_pages_aipage_jsx", "target": "pages_aipage_buildprompt", "relation": "contains", "confidence": "EXTRACTED", "source_file": "E:\\OneDrive\\Desktop\\AGRI_360\\AGRI_360_PROGRAMS\\AgriConnect360Web\\src\\pages\\AIPage.jsx", "source_location": "L62", "weight": 1.0}, {"source": "e_onedrive_desktop_agri_360_agri_360_programs_agriconnect360web_src_pages_aipage_jsx", "target": "pages_aipage_callgroq", "relation": "contains", "confidence": "EXTRACTED", "source_file": "E:\\OneDrive\\Desktop\\AGRI_360\\AGRI_360_PROGRAMS\\AgriConnect360Web\\src\\pages\\AIPage.jsx", "source_location": "L123", "weight": 1.0}, {"source": "e_onedrive_desktop_agri_360_agri_360_programs_agriconnect360web_src_pages_aipage_jsx", "target": "pages_aipage_callgemini", "relation": "contains", "confidence": "EXTRACTED", "source_file": "E:\\OneDrive\\Desktop\\AGRI_360\\AGRI_360_PROGRAMS\\AgriConnect360Web\\src\\pages\\AIPage.jsx", "source_location": "L143", "weight": 1.0}, {"source": "e_onedrive_desktop_agri_360_agri_360_programs_agriconnect360web_src_pages_aipage_jsx", "target": "pages_aipage_callaiengine", "relation": "contains", "confidence": "EXTRACTED", "source_file": "E:\\OneDrive\\Desktop\\AGRI_360\\AGRI_360_PROGRAMS\\AgriConnect360Web\\src\\pages\\AIPage.jsx", "source_location": "L161", "weight": 1.0}, {"source": "e_onedrive_desktop_agri_360_agri_360_programs_agriconnect360web_src_pages_aipage_jsx", "target": "pages_aipage_field", "relation": "contains", "confidence": "EXTRACTED", "source_file": "E:\\OneDrive\\Desktop\\AGRI_360\\AGRI_360_PROGRAMS\\AgriConnect360Web\\src\\pages\\AIPage.jsx", "source_location": "L172", "weight": 1.0}, {"source": "e_onedrive_desktop_agri_360_agri_360_programs_agriconnect360web_src_pages_aipage_jsx", "target": "pages_aipage_getsuggestions", "relation": "contains", "confidence": "EXTRACTED", "source_file": "E:\\OneDrive\\Desktop\\AGRI_360\\AGRI_360_PROGRAMS\\AgriConnect360Web\\src\\pages\\AIPage.jsx", "source_location": "L197", "weight": 1.0}, {"source": "e_onedrive_desktop_agri_360_agri_360_programs_agriconnect360web_src_pages_aipage_jsx", "target": "pages_aipage_aipage", "relation": "contains", "confidence": "EXTRACTED", "source_file": "E:\\OneDrive\\Desktop\\AGRI_360\\AGRI_360_PROGRAMS\\AgriConnect360Web\\src\\pages\\AIPage.jsx", "source_location": "L207", "weight": 1.0}, {"source": "pages_aipage_callaiengine", "target": "pages_aipage_callgroq", "relation": "calls", "confidence": "EXTRACTED", "source_file": "E:\\OneDrive\\Desktop\\AGRI_360\\AGRI_360_PROGRAMS\\AgriConnect360Web\\src\\pages\\AIPage.jsx", "source_location": "L163", "weight": 1.0}, {"source": "pages_aipage_callaiengine", "target": "pages_aipage_callgemini", "relation": "calls", "confidence": "EXTRACTED", "source_file": "E:\\OneDrive\\Desktop\\AGRI_360\\AGRI_360_PROGRAMS\\AgriConnect360Web\\src\\pages\\AIPage.jsx", "source_location": "L167", "weight": 1.0}], "raw_calls": [{"caller_nid": "pages_aipage_istelugutext", "callee": "test", "is_member_call": true, "source_file": "E:\\OneDrive\\Desktop\\AGRI_360\\AGRI_360_PROGRAMS\\AgriConnect360Web\\src\\pages\\AIPage.jsx", "source_location": "L46"}, {"caller_nid": "pages_aipage_callgroq", "callee": "fetch", "is_member_call": false, "source_file": "E:\\OneDrive\\Desktop\\AGRI_360\\AGRI_360_PROGRAMS\\AgriConnect360Web\\src\\pages\\AIPage.jsx", "source_location": "L124"}, {"caller_nid": "pages_aipage_callgroq", "callee": "stringify", "is_member_call": true, "source_file": "E:\\OneDrive\\Desktop\\AGRI_360\\AGRI_360_PROGRAMS\\AgriConnect360Web\\src\\pages\\AIPage.jsx", "source_location": "L127"}, {"caller_nid": "pages_aipage_callgroq", "callee": "json", "is_member_call": true, "source_file": "E:\\OneDrive\\Desktop\\AGRI_360\\AGRI_360_PROGRAMS\\AgriConnect360Web\\src\\pages\\AIPage.jsx", "source_location": "L135"}, {"caller_nid": "pages_aipage_callgroq", "callee": "json", "is_member_call": true, "source_file": "E:\\OneDrive\\Desktop\\AGRI_360\\AGRI_360_PROGRAMS\\AgriConnect360Web\\src\\pages\\AIPage.jsx", "source_location": "L138"}, {"caller_nid": "pages_aipage_callgemini", "callee": "fetch", "is_member_call": false, "source_file": "E:\\OneDrive\\Desktop\\AGRI_360\\AGRI_360_PROGRAMS\\AgriConnect360Web\\src\\pages\\AIPage.jsx", "source_location": "L144"}, {"caller_nid": "pages_aipage_callgemini", "callee": "stringify", "is_member_call": true, "source_file": "E:\\OneDrive\\Desktop\\AGRI_360\\AGRI_360_PROGRAMS\\AgriConnect360Web\\src\\pages\\AIPage.jsx", "source_location": "L147"}, {"caller_nid": "pages_aipage_callgemini", "callee": "json", "is_member_call": true, "source_file": "E:\\OneDrive\\Desktop\\AGRI_360\\AGRI_360_PROGRAMS\\AgriConnect360Web\\src\\pages\\AIPage.jsx", "source_location": "L153"}, {"caller_nid": "pages_aipage_callgemini", "callee": "json", "is_member_call": true, "source_file": "E:\\OneDrive\\Desktop\\AGRI_360\\AGRI_360_PROGRAMS\\AgriConnect360Web\\src\\pages\\AIPage.jsx", "source_location": "L156"}, {"caller_nid": "pages_aipage_callaiengine", "callee": "warn", "is_member_call": true, "source_file": "E:\\OneDrive\\Desktop\\AGRI_360\\AGRI_360_PROGRAMS\\AgriConnect360Web\\src\\pages\\AIPage.jsx", "source_location": "L164"}, {"caller_nid": "pages_aipage_field", "callee": "map", "is_member_call": true, "source_file": "E:\\OneDrive\\Desktop\\AGRI_360\\AGRI_360_PROGRAMS\\AgriConnect360Web\\src\\pages\\AIPage.jsx", "source_location": "L178"}, {"caller_nid": "pages_aipage_getsuggestions", "callee": "toLowerCase", "is_member_call": true, "source_file": "E:\\OneDrive\\Desktop\\AGRI_360\\AGRI_360_PROGRAMS\\AgriConnect360Web\\src\\pages\\AIPage.jsx", "source_location": "L198"}, {"caller_nid": "pages_aipage_getsuggestions", "callee": "includes", "is_member_call": true, "source_file": "E:\\OneDrive\\Desktop\\AGRI_360\\AGRI_360_PROGRAMS\\AgriConnect360Web\\src\\pages\\AIPage.jsx", "source_location": "L199"}, {"caller_nid": "pages_aipage_getsuggestions", "callee": "includes", "is_member_call": true, "source_file": "E:\\OneDrive\\Desktop\\AGRI_360\\AGRI_360_PROGRAMS\\AgriConnect360Web\\src\\pages\\AIPage.jsx", "source_location": "L199"}, {"caller_nid": "pages_aipage_getsuggestions", "callee": "includes", "is_member_call": true, "source_file": "E:\\OneDrive\\Desktop\\AGRI_360\\AGRI_360_PROGRAMS\\AgriConnect360Web\\src\\pages\\AIPage.jsx", "source_location": "L199"}, {"caller_nid": "pages_aipage_getsuggestions", "callee": "includes", "is_member_call": true, "source_file": "E:\\OneDrive\\Desktop\\AGRI_360\\AGRI_360_PROGRAMS\\AgriConnect360Web\\src\\pages\\AIPage.jsx", "source_location": "L199"}, {"caller_nid": "pages_aipage_getsuggestions", "callee": "includes", "is_member_call": true, "source_file": "E:\\OneDrive\\Desktop\\AGRI_360\\AGRI_360_PROGRAMS\\AgriConnect360Web\\src\\pages\\AIPage.jsx", "source_location": "L200"}, {"caller_nid": "pages_aipage_getsuggestions", "callee": "includes", "is_member_call": true, "source_file": "E:\\OneDrive\\Desktop\\AGRI_360\\AGRI_360_PROGRAMS\\AgriConnect360Web\\src\\pages\\AIPage.jsx", "source_location": "L200"}, {"caller_nid": "pages_aipage_getsuggestions", "callee": "includes", "is_member_call": true, "source_file": "E:\\OneDrive\\Desktop\\AGRI_360\\AGRI_360_PROGRAMS\\AgriConnect360Web\\src\\pages\\AIPage.jsx", "source_location": "L200"}, {"caller_nid": "pages_aipage_getsuggestions", "callee": "includes", "is_member_call": true, "source_file": "E:\\OneDrive\\Desktop\\AGRI_360\\AGRI_360_PROGRAMS\\AgriConnect360Web\\src\\pages\\AIPage.jsx", "source_location": "L200"}, {"caller_nid": "pages_aipage_getsuggestions", "callee": "includes", "is_member_call": true, "source_file": "E:\\OneDrive\\Desktop\\AGRI_360\\AGRI_360_PROGRAMS\\AgriConnect360Web\\src\\pages\\AIPage.jsx", "source_location": "L201"}, {"caller_nid": "pages_aipage_getsuggestions", "callee": "includes", "is_member_call": true, "source_file": "E:\\OneDrive\\Desktop\\AGRI_360\\AGRI_360_PROGRAMS\\AgriConnect360Web\\src\\pages\\AIPage.jsx", "source_location": "L201"}, {"caller_nid": "pages_aipage_getsuggestions", "callee": "includes", "is_member_call": true, "source_file": "E:\\OneDrive\\Desktop\\AGRI_360\\AGRI_360_PROGRAMS\\AgriConnect360Web\\src\\pages\\AIPage.jsx", "source_location": "L201"}, {"caller_nid": "pages_aipage_aipage", "callee": "useAuth", "is_member_call": false, "source_file": "E:\\OneDrive\\Desktop\\AGRI_360\\AGRI_360_PROGRAMS\\AgriConnect360Web\\src\\pages\\AIPage.jsx", "source_location": "L208"}, {"caller_nid": "pages_aipage_aipage", "callee": "useState", "is_member_call": false, "source_file": "E:\\OneDrive\\Desktop\\AGRI_360\\AGRI_360_PROGRAMS\\AgriConnect360Web\\src\\pages\\AIPage.jsx", "source_location": "L211"}, {"caller_nid": "pages_aipage_aipage", "callee": "useState", "is_member_call": false, "source_file": "E:\\OneDrive\\Desktop\\AGRI_360\\AGRI_360_PROGRAMS\\AgriConnect360Web\\src\\pages\\AIPage.jsx", "source_location": "L212"}, {"caller_nid": "pages_aipage_aipage", "callee": "useState", "is_member_call": false, "source_file": "E:\\OneDrive\\Desktop\\AGRI_360\\AGRI_360_PROGRAMS\\AgriConnect360Web\\src\\pages\\AIPage.jsx", "source_location": "L213"}, {"caller_nid": "pages_aipage_aipage", "callee": "useState", "is_member_call": false, "source_file": "E:\\OneDrive\\Desktop\\AGRI_360\\AGRI_360_PROGRAMS\\AgriConnect360Web\\src\\pages\\AIPage.jsx", "source_location": "L214"}, {"caller_nid": "pages_aipage_aipage", "callee": "useState", "is_member_call": false, "source_file": "E:\\OneDrive\\Desktop\\AGRI_360\\AGRI_360_PROGRAMS\\AgriConnect360Web\\src\\pages\\AIPage.jsx", "source_location": "L215"}, {"caller_nid": "pages_aipage_aipage", "callee": "useState", "is_member_call": false, "source_file": "E:\\OneDrive\\Desktop\\AGRI_360\\AGRI_360_PROGRAMS\\AgriConnect360Web\\src\\pages\\AIPage.jsx", "source_location": "L217"}, {"caller_nid": "pages_aipage_aipage", "callee": "useState", "is_member_call": false, "source_file": "E:\\OneDrive\\Desktop\\AGRI_360\\AGRI_360_PROGRAMS\\AgriConnect360Web\\src\\pages\\AIPage.jsx", "source_location": "L220"}, {"caller_nid": "pages_aipage_aipage", "callee": "useState", "is_member_call": false, "source_file": "E:\\OneDrive\\Desktop\\AGRI_360\\AGRI_360_PROGRAMS\\AgriConnect360Web\\src\\pages\\AIPage.jsx", "source_location": "L221"}, {"caller_nid": "pages_aipage_aipage", "callee": "useState", "is_member_call": false, "source_file": "E:\\OneDrive\\Desktop\\AGRI_360\\AGRI_360_PROGRAMS\\AgriConnect360Web\\src\\pages\\AIPage.jsx", "source_location": "L222"}, {"caller_nid": "pages_aipage_aipage", "callee": "useState", "is_member_call": false, "source_file": "E:\\OneDrive\\Desktop\\AGRI_360\\AGRI_360_PROGRAMS\\AgriConnect360Web\\src\\pages\\AIPage.jsx", "source_location": "L223"}, {"caller_nid": "pages_aipage_aipage", "callee": "useRef", "is_member_call": false, "source_file": "E:\\OneDrive\\Desktop\\AGRI_360\\AGRI_360_PROGRAMS\\AgriConnect360Web\\src\\pages\\AIPage.jsx", "source_location": "L224"}, {"caller_nid": "pages_aipage_aipage", "callee": "useEffect", "is_member_call": false, "source_file": "E:\\OneDrive\\Desktop\\AGRI_360\\AGRI_360_PROGRAMS\\AgriConnect360Web\\src\\pages\\AIPage.jsx", "source_location": "L226"}, {"caller_nid": "pages_aipage_aipage", "callee": "useEffect", "is_member_call": false, "source_file": "E:\\OneDrive\\Desktop\\AGRI_360\\AGRI_360_PROGRAMS\\AgriConnect360Web\\src\\pages\\AIPage.jsx", "source_location": "L227"}, {"caller_nid": "pages_aipage_aipage", "callee": "useState", "is_member_call": false, "source_file": "E:\\OneDrive\\Desktop\\AGRI_360\\AGRI_360_PROGRAMS\\AgriConnect360Web\\src\\pages\\AIPage.jsx", "source_location": "L229"}, {"caller_nid": "pages_aipage_aipage", "callee": "useState", "is_member_call": false, "source_file": "E:\\OneDrive\\Desktop\\AGRI_360\\AGRI_360_PROGRAMS\\AgriConnect360Web\\src\\pages\\AIPage.jsx", "source_location": "L234"}, {"caller_nid": "pages_aipage_aipage", "callee": "useState", "is_member_call": false, "source_file": "E:\\OneDrive\\Desktop\\AGRI_360\\AGRI_360_PROGRAMS\\AgriConnect360Web\\src\\pages\\AIPage.jsx", "source_location": "L235"}, {"caller_nid": "pages_aipage_aipage", "callee": "useState", "is_member_call": false, "source_file": "E:\\OneDrive\\Desktop\\AGRI_360\\AGRI_360_PROGRAMS\\AgriConnect360Web\\src\\pages\\AIPage.jsx", "source_location": "L236"}, {"caller_nid": "pages_aipage_aipage", "callee": "useState", "is_member_call": false, "source_file": "E:\\OneDrive\\Desktop\\AGRI_360\\AGRI_360_PROGRAMS\\AgriConnect360Web\\src\\pages\\AIPage.jsx", "source_location": "L237"}, {"caller_nid": "pages_aipage_aipage", "callee": "useState", "is_member_call": false, "source_file": "E:\\OneDrive\\Desktop\\AGRI_360\\AGRI_360_PROGRAMS\\AgriConnect360Web\\src\\pages\\AIPage.jsx", "source_location": "L238"}, {"caller_nid": "pages_aipage_aipage", "callee": "useState", "is_member_call": false, "source_file": "E:\\OneDrive\\Desktop\\AGRI_360\\AGRI_360_PROGRAMS\\AgriConnect360Web\\src\\pages\\AIPage.jsx", "source_location": "L239"}, {"caller_nid": "pages_aipage_aipage", "callee": "useState", "is_member_call": false, "source_file": "E:\\OneDrive\\Desktop\\AGRI_360\\AGRI_360_PROGRAMS\\AgriConnect360Web\\src\\pages\\AIPage.jsx", "source_location": "L240"}, {"caller_nid": "pages_aipage_aipage", "callee": "useState", "is_member_call": false, "source_file": "E:\\OneDrive\\Desktop\\AGRI_360\\AGRI_360_PROGRAMS\\AgriConnect360Web\\src\\pages\\AIPage.jsx", "source_location": "L241"}, {"caller_nid": "pages_aipage_aipage", "callee": "useState", "is_member_call": false, "source_file": "E:\\OneDrive\\Desktop\\AGRI_360\\AGRI_360_PROGRAMS\\AgriConnect360Web\\src\\pages\\AIPage.jsx", "source_location": "L242"}, {"caller_nid": "pages_aipage_aipage", "callee": "useState", "is_member_call": false, "source_file": "E:\\OneDrive\\Desktop\\AGRI_360\\AGRI_360_PROGRAMS\\AgriConnect360Web\\src\\pages\\AIPage.jsx", "source_location": "L243"}, {"caller_nid": "pages_aipage_aipage", "callee": "useState", "is_member_call": false, "source_file": "E:\\OneDrive\\Desktop\\AGRI_360\\AGRI_360_PROGRAMS\\AgriConnect360Web\\src\\pages\\AIPage.jsx", "source_location": "L244"}, {"caller_nid": "pages_aipage_aipage", "callee": "useState", "is_member_call": false, "source_file": "E:\\OneDrive\\Desktop\\AGRI_360\\AGRI_360_PROGRAMS\\AgriConnect360Web\\src\\pages\\AIPage.jsx", "source_location": "L245"}, {"caller_nid": "pages_aipage_aipage", "callee": "useState", "is_member_call": false, "source_file": "E:\\OneDrive\\Desktop\\AGRI_360\\AGRI_360_PROGRAMS\\AgriConnect360Web\\src\\pages\\AIPage.jsx", "source_location": "L246"}, {"caller_nid": "pages_aipage_aipage", "callee": "useState", "is_member_call": false, "source_file": "E:\\OneDrive\\Desktop\\AGRI_360\\AGRI_360_PROGRAMS\\AgriConnect360Web\\src\\pages\\AIPage.jsx", "source_location": "L247"}, {"caller_nid": "pages_aipage_aipage", "callee": "find", "is_member_call": true, "source_file": "E:\\OneDrive\\Desktop\\AGRI_360\\AGRI_360_PROGRAMS\\AgriConnect360Web\\src\\pages\\AIPage.jsx", "source_location": "L409"}, {"caller_nid": "pages_aipage_aipage", "callee": "map", "is_member_call": true, "source_file": "E:\\OneDrive\\Desktop\\AGRI_360\\AGRI_360_PROGRAMS\\AgriConnect360Web\\src\\pages\\AIPage.jsx", "source_location": "L465"}, {"caller_nid": "pages_aipage_aipage", "callee": "map", "is_member_call": true, "source_file": "E:\\OneDrive\\Desktop\\AGRI_360\\AGRI_360_PROGRAMS\\AgriConnect360Web\\src\\pages\\AIPage.jsx", "source_location": "L468"}, {"caller_nid": "pages_aipage_aipage", "callee": "map", "is_member_call": true, "source_file": "E:\\OneDrive\\Desktop\\AGRI_360\\AGRI_360_PROGRAMS\\AgriConnect360Web\\src\\pages\\AIPage.jsx", "source_location": "L502"}, {"caller_nid": "pages_aipage_aipage", "callee": "map", "is_member_call": true, "source_file": "E:\\OneDrive\\Desktop\\AGRI_360\\AGRI_360_PROGRAMS\\AgriConnect360Web\\src\\pages\\AIPage.jsx", "source_location": "L535"}, {"caller_nid": "pages_aipage_aipage", "callee": "map", "is_member_call": true, "source_file": "E:\\OneDrive\\Desktop\\AGRI_360\\AGRI_360_PROGRAMS\\AgriConnect360Web\\src\\pages\\AIPage.jsx", "source_location": "L561"}, {"caller_nid": "pages_aipage_aipage", "callee": "map", "is_member_call": true, "source_file": "E:\\OneDrive\\Desktop\\AGRI_360\\AGRI_360_PROGRAMS\\AgriConnect360Web\\src\\pages\\AIPage.jsx", "source_location": "L584"}, {"caller_nid": "pages_aipage_aipage", "callee": "map", "is_member_call": true, "source_file": "E:\\OneDrive\\Desktop\\AGRI_360\\AGRI_360_PROGRAMS\\AgriConnect360Web\\src\\pages\\AIPage.jsx", "source_location": "L636"}, {"caller_nid": "pages_aipage_aipage", "callee": "map", "is_member_call": true, "source_file": "E:\\OneDrive\\Desktop\\AGRI_360\\AGRI_360_PROGRAMS\\AgriConnect360Web\\src\\pages\\AIPage.jsx", "source_location": "L653"}, {"caller_nid": "pages_aipage_aipage", "callee": "trim", "is_member_call": true, "source_file": "E:\\OneDrive\\Desktop\\AGRI_360\\AGRI_360_PROGRAMS\\AgriConnect360Web\\src\\pages\\AIPage.jsx", "source_location": "L700"}, {"caller_nid": "pages_aipage_aipage", "callee": "map", "is_member_call": true, "source_file": "E:\\OneDrive\\Desktop\\AGRI_360\\AGRI_360_PROGRAMS\\AgriConnect360Web\\src\\pages\\AIPage.jsx", "source_location": "L734"}, {"caller_nid": "pages_aipage_aipage", "callee": "map", "is_member_call": true, "source_file": "E:\\OneDrive\\Desktop\\AGRI_360\\AGRI_360_PROGRAMS\\AgriConnect360Web\\src\\pages\\AIPage.jsx", "source_location": "L755"}, {"caller_nid": "pages_aipage_aipage", "callee": "map", "is_member_call": true, "source_file": "E:\\OneDrive\\Desktop\\AGRI_360\\AGRI_360_PROGRAMS\\AgriConnect360Web\\src\\pages\\AIPage.jsx", "source_location": "L828"}, {"caller_nid": "pages_aipage_aipage", "callee": "map", "is_member_call": true, "source_file": "E:\\OneDrive\\Desktop\\AGRI_360\\AGRI_360_PROGRAMS\\AgriConnect360Web\\src\\pages\\AIPage.jsx", "source_location": "L896"}]}