{"nodes": [{"id": "e_onedrive_desktop_agri_360_agri_360_programs_agriconnect360web_src_pages_dashboard_jsx", "label": "Dashboard.jsx", "file_type": "code", "source_file": "E:\\OneDrive\\Desktop\\AGRI_360\\AGRI_360_PROGRAMS\\AgriConnect360Web\\src\\pages\\Dashboard.jsx", "source_location": "L1"}, {"id": "pages_dashboard_dashboard", "label": "Dashboard()", "file_type": "code", "source_file": "E:\\OneDrive\\Desktop\\AGRI_360\\AGRI_360_PROGRAMS\\AgriConnect360Web\\src\\pages\\Dashboard.jsx", "source_location": "L45"}], "edges": [{"source": "e_onedrive_desktop_agri_360_agri_360_programs_agriconnect360web_src_pages_dashboard_jsx", "target": "react", "relation": "imports_from", "confidence": "EXTRACTED", "source_file": "E:\\OneDrive\\Desktop\\AGRI_360\\AGRI_360_PROGRAMS\\AgriConnect360Web\\src\\pages\\Dashboard.jsx", "source_location": "L1", "weight": 1.0}, {"source": "e_onedrive_desktop_agri_360_agri_360_programs_agriconnect360web_src_pages_dashboard_jsx", "target": "react_router_dom", "relation": "imports_from", "confidence": "EXTRACTED", "source_file": "E:\\OneDrive\\Desktop\\AGRI_360\\AGRI_360_PROGRAMS\\AgriConnect360Web\\src\\pages\\Dashboard.jsx", "source_location": "L2", "weight": 1.0}, {"source": "e_onedrive_desktop_agri_360_agri_360_programs_agriconnect360web_src_pages_dashboard_jsx", "target": "e_onedrive_desktop_agri_360_agri_360_programs_agriconnect360web_src_lib_supabase", "relation": "imports_from", "confidence": "EXTRACTED", "source_file": "E:\\OneDrive\\Desktop\\AGRI_360\\AGRI_360_PROGRAMS\\AgriConnect360Web\\src\\pages\\Dashboard.jsx", "source_location": "L3", "weight": 1.0}, {"source": "e_onedrive_desktop_agri_360_agri_360_programs_agriconnect360web_src_pages_dashboard_jsx", "target": "e_onedrive_desktop_agri_360_agri_360_programs_agriconnect360web_src_lib_i18n_languagecontext", "relation": "imports_from", "confidence": "EXTRACTED", "source_file": "E:\\OneDrive\\Desktop\\AGRI_360\\AGRI_360_PROGRAMS\\AgriConnect360Web\\src\\pages\\Dashboard.jsx", "source_location": "L4", "weight": 1.0}, {"source": "e_onedrive_desktop_agri_360_agri_360_programs_agriconnect360web_src_pages_dashboard_jsx", "target": "pages_dashboard_dashboard", "relation": "contains", "confidence": "EXTRACTED", "source_file": "E:\\OneDrive\\Desktop\\AGRI_360\\AGRI_360_PROGRAMS\\AgriConnect360Web\\src\\pages\\Dashboard.jsx", "source_location": "L45", "weight": 1.0}], "raw_calls": [{"caller_nid": "pages_dashboard_dashboard", "callee": "useNavigate", "is_member_call": false, "source_file": "E:\\OneDrive\\Desktop\\AGRI_360\\AGRI_360_PROGRAMS\\AgriConnect360Web\\src\\pages\\Dashboard.jsx", "source_location": "L46"}, {"caller_nid": "pages_dashboard_dashboard", "callee": "useLanguage", "is_member_call": false, "source_file": "E:\\OneDrive\\Desktop\\AGRI_360\\AGRI_360_PROGRAMS\\AgriConnect360Web\\src\\pages\\Dashboard.jsx", "source_location": "L47"}, {"caller_nid": "pages_dashboard_dashboard", "callee": "useState", "is_member_call": false, "source_file": "E:\\OneDrive\\Desktop\\AGRI_360\\AGRI_360_PROGRAMS\\AgriConnect360Web\\src\\pages\\Dashboard.jsx", "source_location": "L48"}, {"caller_nid": "pages_dashboard_dashboard", "callee": "useState", "is_member_call": false, "source_file": "E:\\OneDrive\\Desktop\\AGRI_360\\AGRI_360_PROGRAMS\\AgriConnect360Web\\src\\pages\\Dashboard.jsx", "source_location": "L49"}, {"caller_nid": "pages_dashboard_dashboard", "callee": "useState", "is_member_call": false, "source_file": "E:\\OneDrive\\Desktop\\AGRI_360\\AGRI_360_PROGRAMS\\AgriConnect360Web\\src\\pages\\Dashboard.jsx", "source_location": "L50"}, {"caller_nid": "pages_dashboard_dashboard", "callee": "useState", "is_member_call": false, "source_file": "E:\\OneDrive\\Desktop\\AGRI_360\\AGRI_360_PROGRAMS\\AgriConnect360Web\\src\\pages\\Dashboard.jsx", "source_location": "L51"}, {"caller_nid": "pages_dashboard_dashboard", "callee": "useEffect", "is_member_call": false, "source_file": "E:\\OneDrive\\Desktop\\AGRI_360\\AGRI_360_PROGRAMS\\AgriConnect360Web\\src\\pages\\Dashboard.jsx", "source_location": "L53"}, {"caller_nid": "pages_dashboard_dashboard", "callee": "toLocaleDateString", "is_member_call": true, "source_file": "E:\\OneDrive\\Desktop\\AGRI_360\\AGRI_360_PROGRAMS\\AgriConnect360Web\\src\\pages\\Dashboard.jsx", "source_location": "L99"}, {"caller_nid": "pages_dashboard_dashboard", "callee": "map", "is_member_call": true, "source_file": "E:\\OneDrive\\Desktop\\AGRI_360\\AGRI_360_PROGRAMS\\AgriConnect360Web\\src\\pages\\Dashboard.jsx", "source_location": "L104"}, {"caller_nid": "pages_dashboard_dashboard", "callee": "map", "is_member_call": true, "source_file": "E:\\OneDrive\\Desktop\\AGRI_360\\AGRI_360_PROGRAMS\\AgriConnect360Web\\src\\pages\\Dashboard.jsx", "source_location": "L124"}, {"caller_nid": "pages_dashboard_dashboard", "callee": "filter", "is_member_call": true, "source_file": "E:\\OneDrive\\Desktop\\AGRI_360\\AGRI_360_PROGRAMS\\AgriConnect360Web\\src\\pages\\Dashboard.jsx", "source_location": "L139"}, {"caller_nid": "pages_dashboard_dashboard", "callee": "map", "is_member_call": true, "source_file": "E:\\OneDrive\\Desktop\\AGRI_360\\AGRI_360_PROGRAMS\\AgriConnect360Web\\src\\pages\\Dashboard.jsx", "source_location": "L141"}]}